odoo10_addon_stock_move_backdating-10.0.1.0.0.99.dev9-py3.8-nspkg.pth
odoo/addons/stock_move_backdating/README.rst
odoo/addons/stock_move_backdating/__init__.py
odoo/addons/stock_move_backdating/__manifest__.py
odoo/addons/stock_move_backdating/i18n/am.po
odoo/addons/stock_move_backdating/i18n/ca.po
odoo/addons/stock_move_backdating/i18n/de.po
odoo/addons/stock_move_backdating/i18n/es.po
odoo/addons/stock_move_backdating/i18n/es_AR.po
odoo/addons/stock_move_backdating/i18n/es_MX.po
odoo/addons/stock_move_backdating/i18n/fi.po
odoo/addons/stock_move_backdating/i18n/fr.po
odoo/addons/stock_move_backdating/i18n/gl.po
odoo/addons/stock_move_backdating/i18n/hr.po
odoo/addons/stock_move_backdating/i18n/hr_HR.po
odoo/addons/stock_move_backdating/i18n/it.po
odoo/addons/stock_move_backdating/i18n/nl.po
odoo/addons/stock_move_backdating/i18n/pt.po
odoo/addons/stock_move_backdating/i18n/pt_BR.po
odoo/addons/stock_move_backdating/i18n/pt_PT.po
odoo/addons/stock_move_backdating/i18n/ro.po
odoo/addons/stock_move_backdating/i18n/sl.po
odoo/addons/stock_move_backdating/i18n/stock_move_backdating.pot
odoo/addons/stock_move_backdating/i18n/tr.po
odoo/addons/stock_move_backdating/i18n/tr_TR.po
odoo/addons/stock_move_backdating/models/__init__.py
odoo/addons/stock_move_backdating/models/stock_move.py
odoo/addons/stock_move_backdating/models/stock_pack_operation.py
odoo/addons/stock_move_backdating/models/stock_picking.py
odoo/addons/stock_move_backdating/static/description/icon.png
odoo/addons/stock_move_backdating/tests/__init__.py
odoo/addons/stock_move_backdating/tests/test_stock_move_backdating.py
odoo/addons/stock_move_backdating/views/stock_picking.xml
odoo/addons/stock_move_backdating/wizards/__init__.py
odoo/addons/stock_move_backdating/wizards/fill_date_backdating.py
odoo/addons/stock_move_backdating/wizards/fill_date_backdating.xml
odoo10_addon_stock_move_backdating-10.0.1.0.0.99.dev9.dist-info/METADATA
odoo10_addon_stock_move_backdating-10.0.1.0.0.99.dev9.dist-info/WHEEL
odoo10_addon_stock_move_backdating-10.0.1.0.0.99.dev9.dist-info/namespace_packages.txt
odoo10_addon_stock_move_backdating-10.0.1.0.0.99.dev9.dist-info/top_level.txt
odoo10_addon_stock_move_backdating-10.0.1.0.0.99.dev9.dist-info/RECORD
